pgantomizer/__init__.py
pgantomizer/anonymize.py
pgantomizer/dump.py
pgantomizer/utils.py
pgantomizer-0.1.0.dist-info/DESCRIPTION.rst
pgantomizer-0.1.0.dist-info/METADATA
pgantomizer-0.1.0.dist-info/RECORD
pgantomizer-0.1.0.dist-info/WHEEL
pgantomizer-0.1.0.dist-info/entry_points.txt
pgantomizer-0.1.0.dist-info/metadata.json
pgantomizer-0.1.0.dist-info/top_level.txt
tests/__init__.py
tests/asserts.py
tests/test_pgantomizer.py
