Metadata-Version: 2.0
Name: pgantomizer
Version: 0.1.0
Summary: Anonymize data in your PostgreSQL dababase with ease.
Home-page: https://github.com/asgeirrr/pgantomizer
Author: Oskar Hollmann
Author-email: oskar@hollmann.me
License: BSD
Keywords: postgres anonymization dump
Platform: UNKNOWN
Classifier: Development Status :: 4 - Beta
Classifier: Environment :: Console
Classifier: Intended Audience :: Developers
Classifier: License :: OSI Approved :: BSD License
Classifier: Operating System :: OS Independent
Classifier: Programming Language :: Python :: 3.6
Classifier: Topic :: Database :: Front-Ends
Requires-Dist: psycopg2 (>=2.6.1)
Requires-Dist: pyyaml (>=3.11)
